discord/__init__.py
discord/api.py
discord/bot.py
discord/channel.py
discord/embed.py
discord/emoji.py
discord/gateway.py
discord/gateway_protocol.py
discord/guild.py
discord/guild_member.py
discord/helpful_functions.py
discord/interaction.py
discord/message.py
discord/role.py
discord/user.py
bad_discord-0.0.2.dist-info/LICENSE
bad_discord-0.0.2.dist-info/METADATA
bad_discord-0.0.2.dist-info/WHEEL
bad_discord-0.0.2.dist-info/top_level.txt
bad_discord-0.0.2.dist-info/RECORD
