Metadata-Version: 2.1
Name: bad-discord
Version: 0.0.2
Summary: A simple wrapper for discord API
Author: BattleTonk
Keywords: python,discord bots
Classifier: Development Status :: 1 - Planning
Classifier: Intended Audience :: Developers
Classifier: Programming Language :: Python :: 3
Classifier: Operating System :: Unix
Classifier: Operating System :: MacOS :: MacOS X
Classifier: Operating System :: Microsoft :: Windows
License-File: LICENSE
Requires-Dist: websockets
Requires-Dist: requests
